fastapi_swagger_splitter/__init__.py
fastapi_swagger_splitter/splitter.py
fastapi_swagger_splitter-0.1.2.dist-info/licenses/LICENSE
fastapi_swagger_splitter-0.1.2.dist-info/METADATA
fastapi_swagger_splitter-0.1.2.dist-info/WHEEL
fastapi_swagger_splitter-0.1.2.dist-info/top_level.txt
fastapi_swagger_splitter-0.1.2.dist-info/RECORD
