Metadata-Version: 2.4
Name: fastapi-swagger-splitter
Version: 0.1.2
Summary: Enhanced Swagger UI for FastAPI with tag-based filtering and download links
Author-email: Your Name <your.email@example.com>
License-Expression: MIT
Project-URL: Homepage, https://github.com/yourusername/fastapi-swagger-splitter
Project-URL: Documentation, https://github.com/yourusername/fastapi-swagger-splitter#readme
Project-URL: Repository, https://github.com/yourusername/fastapi-swagger-splitter
Project-URL: Issues, https://github.com/yourusername/fastapi-swagger-splitter/issues
Keywords: fastapi,swagger,openapi,api-documentation,splitter
Classifier: Development Status :: 4 - Beta
Classifier: Intended Audience :: Developers
Classifier: Programming Language :: Python :: 3
Classifier: Programming Language :: Python :: 3.8
Classifier: Programming Language :: Python :: 3.9
Classifier: Programming Language :: Python :: 3.10
Classifier: Programming Language :: Python :: 3.11
Classifier: Programming Language :: Python :: 3.12
Classifier: Framework :: FastAPI
Requires-Python: >=3.8
License-File: LICENSE
Requires-Dist: fastapi>=0.68.0
Requires-Dist: starlette>=0.14.0
Provides-Extra: dev
Requires-Dist: pytest>=7.0.0; extra == "dev"
Requires-Dist: pytest-asyncio>=0.21.0; extra == "dev"
Requires-Dist: black>=23.0.0; extra == "dev"
Requires-Dist: ruff>=0.1.0; extra == "dev"
Dynamic: license-file
